LICENSE
requirements.txt
setup.py
docs/README.md
fromconfig/__init__.py
fromconfig/version.py
fromconfig.egg-info/PKG-INFO
fromconfig.egg-info/SOURCES.txt
fromconfig.egg-info/dependency_links.txt
fromconfig.egg-info/entry_points.txt
fromconfig.egg-info/requires.txt
fromconfig.egg-info/top_level.txt
fromconfig/cli/__init__.py
fromconfig/cli/main.py
fromconfig/core/__init__.py
fromconfig/core/base.py
fromconfig/core/config.py
fromconfig/launcher/__init__.py
fromconfig/launcher/base.py
fromconfig/launcher/default.py
fromconfig/launcher/dry.py
fromconfig/launcher/hparams.py
fromconfig/launcher/local.py
fromconfig/launcher/logger.py
fromconfig/launcher/parser.py
fromconfig/parser/__init__.py
fromconfig/parser/base.py
fromconfig/parser/default.py
fromconfig/parser/evaluate.py
fromconfig/parser/omega.py
fromconfig/parser/singleton.py
fromconfig/utils/__init__.py
fromconfig/utils/libimport.py
fromconfig/utils/nest.py
fromconfig/utils/strenum.py
fromconfig/utils/testing.py
fromconfig/utils/types.py
tests/__init__.py
tests/unit/__init__.py
tests/unit/cli/__init__.py
tests/unit/cli/test_cli_main.py
tests/unit/core/__init__.py
tests/unit/core/test_core_base.py
tests/unit/core/test_core_config.py
tests/unit/launcher/__init__.py
tests/unit/launcher/test_launcher_base.py
tests/unit/launcher/test_launcher_default.py
tests/unit/launcher/test_launcher_dry.py
tests/unit/launcher/test_launcher_hparams.py
tests/unit/launcher/test_launcher_local.py
tests/unit/launcher/test_launcher_logger.py
tests/unit/launcher/test_launcher_parser.py
tests/unit/parser/__init__.py
tests/unit/parser/test_parser_base.py
tests/unit/parser/test_parser_default.py
tests/unit/parser/test_parser_evaluate.py
tests/unit/parser/test_parser_omegaconf.py
tests/unit/parser/test_parser_singleton.py
tests/unit/utils/__init__.py
tests/unit/utils/test_utils_libimport.py
tests/unit/utils/test_utils_nest.py
tests/unit/utils/test_utils_strenum.py
tests/unit/utils/test_utils_types.py