Metadata-Version: 2.1
Name: fromconfig
Version: 0.7.0
Summary: A library to instantiate any Python object from configuration files
Home-page: https://github.com/criteo/fromconfig
Author: Criteo
License: UNKNOWN
Platform: UNKNOWN
Classifier: License :: OSI Approved :: Apache Software License
Classifier: Operating System :: OS Independent
Classifier: Programming Language :: Python :: 3.6
Classifier: Programming Language :: Python :: 3.7
Classifier: Programming Language :: Python :: 3.8
Classifier: Programming Language :: Python :: 3.9
Classifier: Intended Audience :: Developers
License-File: LICENSE
